aquirdturtle_collapsible_headings/__init__.py
aquirdturtle_collapsible_headings/_version.py
aquirdturtle_collapsible_headings/labextension/package.json
aquirdturtle_collapsible_headings/labextension/schemas/@aquirdturtle/collapsible_headings/package.json.orig
aquirdturtle_collapsible_headings/labextension/schemas/@aquirdturtle/collapsible_headings/plugin.json
aquirdturtle_collapsible_headings/labextension/static/341.f9093d1e2d6aaa40cf76.js
aquirdturtle_collapsible_headings/labextension/static/534.b9af8af45c8afe8f82cd.js
aquirdturtle_collapsible_headings/labextension/static/568.69dd4e4f1ed0702636a5.js
aquirdturtle_collapsible_headings/labextension/static/568.b1a7cff15987d9d3b68f.js
aquirdturtle_collapsible_headings/labextension/static/remoteEntry.18eeb82ef4decd238fe8.js
aquirdturtle_collapsible_headings/labextension/static/remoteEntry.770029ea89527691bc5a.js
aquirdturtle_collapsible_headings/labextension/static/remoteEntry.b4f789b51f37c326ac00.js
aquirdturtle_collapsible_headings/labextension/static/style.js
aquirdturtle_collapsible_headings-3.1.0.data/data/share/jupyter/labextensions/@aquirdturtle/collapsible_headings/install.json
aquirdturtle_collapsible_headings-3.1.0.data/data/share/jupyter/labextensions/@aquirdturtle/collapsible_headings/package.json
aquirdturtle_collapsible_headings-3.1.0.data/data/share/jupyter/labextensions/@aquirdturtle/collapsible_headings/schemas/@aquirdturtle/collapsible_headings/package.json.orig
aquirdturtle_collapsible_headings-3.1.0.data/data/share/jupyter/labextensions/@aquirdturtle/collapsible_headings/schemas/@aquirdturtle/collapsible_headings/plugin.json
aquirdturtle_collapsible_headings-3.1.0.data/data/share/jupyter/labextensions/@aquirdturtle/collapsible_headings/static/341.f9093d1e2d6aaa40cf76.js
aquirdturtle_collapsible_headings-3.1.0.data/data/share/jupyter/labextensions/@aquirdturtle/collapsible_headings/static/534.b9af8af45c8afe8f82cd.js
aquirdturtle_collapsible_headings-3.1.0.dist-info/LICENSE
aquirdturtle_collapsible_headings-3.1.0.dist-info/METADATA
aquirdturtle_collapsible_headings-3.1.0.dist-info/WHEEL
aquirdturtle_collapsible_headings-3.1.0.dist-info/top_level.txt
aquirdturtle_collapsible_headings-3.1.0.dist-info/RECORD
