Metadata-Version: 2.1
Name: aquirdturtle-collapsible-headings
Version: 3.1.0
Summary: Make headings collapsible like the old Jupyter notebook extension and like mathematica notebooks.
Home-page: https://github.com/aquirdTurtle/Collapsible_Headings.git
Author: Mark O Brown
License: BSD-3-Clause
Keywords: Jupyter,JupyterLab,JupyterLab3
Platform: Linux
Platform: Mac OS X
Platform: Windows
Classifier: License :: OSI Approved :: BSD License
Classifier: Programming Language :: Python
Classifier: Programming Language :: Python :: 3
Classifier: Programming Language :: Python :: 3.6
Classifier: Programming Language :: Python :: 3.7
Classifier: Programming Language :: Python :: 3.8
Classifier: Framework :: Jupyter
Requires-Python: >=3.6
Requires-Dist: jupyterlab (==3.*,>=3.0.0rc13)
